{
    "country": "Gambia",
    "overview": {
        "tax_residency_rules": "Determined by physical presence for more than 183 days in a tax year.",
        "tax_year": "Calendar year (January 1 - December 31).",
        "currency": "Dalasi (GMD)",
        "tax_authority": "Gambia Revenue Authority",
        "tax_filing_frequency": "Annually.",
        "currency_exchange_rules": "No restrictions on currency conversion."
    },
    "tax_rates": {
        "personal_income_tax": {
            "rate": [
                {
                    "bracket": "0 - 40,000 GMD",
                    "rate": "0%"
                },
                {
                    "bracket": "40,001 - 60,000 GMD",
                    "rate": "15%"
                },
                {
                    "bracket": "60,001+ GMD",
                    "rate": "25%"
                }
            ],
            "foreign_income_taxed": false,
            "exemptions": "First 40,000 GMD of income is tax-free.",
            "social_security": "Information not available."
        },
        "corporate_tax": {
            "rate": "30% on net profits.",
            "small_business_rate": "15% for businesses with turnover below 500,000 GMD.",
            "foreign_income_taxed": false,
            "withholding_taxes": {
                "dividends": "15%",
                "interest": "15%",
                "royalties": "15%"
            },
            "deductions": "Business expenses, depreciation."
        },
        "capital_gains_tax": {
            "rate": [
                {
                    "asset_type": "Stocks",
                    "short_term_rate": "Information not available.",
                    "long_term_rate": "15%."
                },
                {
                    "asset_type": "Real Estate",
                    "short_term_rate": "Information not available.",
                    "long_term_rate": "15%."
                },
                {
                    "asset_type": "Collectibles/NFTs",
                    "short_term_rate": "Information not available.",
                    "long_term_rate": "15%."
                }
            ],
            "exemptions": "Primary residence is exempt."
        },
        "vat_gst": {
            "rate": "15% on most goods and services.",
            "reduced_rate": "Information not available.",
            "exemptions": "Healthcare, education, basic food items."
        },
        "property_tax": {
            "rate": "Information not available.",
            "exemptions": "Information not available."
        },
        "inheritance_tax": {
            "rate": "Information not available.",
            "exemptions": "Information not available."
        },
        "wealth_tax": {
            "rate": "Information not available.",
            "exemptions": "Information not available."
        }
    },
    "digital_nomad_visa": {
        "available": false,
        "requirements": "N/A",
        "tax_benefits": "N/A",
        "duration": "N/A"
    },
    "special_economic_zones": [],
    "double_taxation_agreements": [],
    "crypto_and_nft_taxation": {
        "crypto_tax": {
            "income_tax_rate": "Information not available.",
            "capital_gains_rate": "Information not available.",
            "mining_tax": "Information not available."
        },
        "nft_tax": {
            "income_tax_rate": "Information not available.",
            "capital_gains_rate": "Information not available."
        }
    },
    "additional_notes": {
        "political_risks": "Political instability may impact tax policies and enforcement.",
        "economic_stability": "Economic instability may affect tax revenues and tax rates.",
        "legal_system": "Tax laws and regulations may be subject to change.",
        "ease_of_doing_business": "Ranked 143rd in the World Bank's Ease of Doing Business Index."
    }
}